warp_loss/__init__.py
warp_loss/_nbdev.py
warp_loss/losses.py
warp_loss-0.0.1.dist-info/LICENSE
warp_loss-0.0.1.dist-info/METADATA
warp_loss-0.0.1.dist-info/WHEEL
warp_loss-0.0.1.dist-info/entry_points.txt
warp_loss-0.0.1.dist-info/top_level.txt
warp_loss-0.0.1.dist-info/RECORD
