Metadata-Version: 2.1
Name: warp-loss
Version: 0.0.1
Summary: "WARP loss for Pytorch. WSABIE"
Home-page: https://github.com/NegatioN/WARP-Pytorch
Author: "Joakim Rishaug"
Author-email: "joakimrishaug@notmyrealemail.com"
License: Apache Software License 2.0
Keywords: pytorch loss WARP WSABIE
Platform: UNKNOWN
Classifier: Development Status :: 3 - Alpha
Classifier: Intended Audience :: Developers
Classifier: License :: OSI Approved :: Apache Software License
Classifier: Natural Language :: English
Classifier: Programming Language :: Python :: 3.6
Classifier: Programming Language :: Python :: 3.7
Classifier: Programming Language :: Python :: 3.8
Requires-Python: >=3.6
Requires-Dist: numpy (>=1.15.4)
Requires-Dist: torch (>=0.4.1)
